dakka/__init__.py
dakka/agent_logger.py
dakka/ask.py
dakka/cli.py
dakka/openapi_spec.py
dakka/test_cli.py
dakka/utils.py
dakka-0.1.2.dist-info/METADATA
dakka-0.1.2.dist-info/WHEEL
dakka-0.1.2.dist-info/entry_points.txt
dakka-0.1.2.dist-info/top_level.txt
dakka-0.1.2.dist-info/RECORD
